{
  "content": [
    {
      "content": null,
      "created": "2024-10-18T15:22:04.025944Z",
      "format": null,
      "hash": null,
      "hash_algorithm": null,
      "last_modified": "2024-10-18T15:21:55.005925Z",
      "mimetype": null,
      "name": "template_arrange.ipynb",
      "path": "how_to/templates/template_arrange.ipynb",
      "size": 2791,
      "type": "notebook",
      "writable": true
    },
    {
      "content": null,
      "created": "2024-10-18T15:22:04.025944Z",
      "format": null,
      "hash": null,
      "hash_algorithm": null,
      "last_modified": "2024-10-18T15:21:55.009925Z",
      "mimetype": null,
      "name": "template_set.ipynb",
      "path": "how_to/templates/template_set.ipynb",
      "size": 4735,
      "type": "notebook",
      "writable": true
    },
    {
      "content": null,
      "created": "2024-10-18T15:22:04.025944Z",
      "format": null,
      "hash": null,
      "hash_algorithm": null,
      "last_modified": "2024-10-18T15:21:55.005925Z",
      "mimetype": null,
      "name": "template_custom.ipynb",
      "path": "how_to/templates/template_custom.ipynb",
      "size": 10107,
      "type": "notebook",
      "writable": true
    },
    {
      "content": null,
      "created": "2024-10-18T15:22:04.025944Z",
      "format": null,
      "hash": null,
      "hash_algorithm": null,
      "last_modified": "2024-10-18T15:21:55.009925Z",
      "mimetype": null,
      "name": "template_modal.ipynb",
      "path": "how_to/templates/template_modal.ipynb",
      "size": 3093,
      "type": "notebook",
      "writable": true
    },
    {
      "content": null,
      "created": "2024-10-18T15:22:04.025944Z",
      "format": null,
      "hash": null,
      "hash_algorithm": null,
      "last_modified": "2024-10-18T15:21:55.009925Z",
      "mimetype": null,
      "name": "template_theme.ipynb",
      "path": "how_to/templates/template_theme.ipynb",
      "size": 3418,
      "type": "notebook",
      "writable": true
    }
  ],
  "created": "2024-10-18T15:22:04.025944Z",
  "format": "json",
  "hash": null,
  "hash_algorithm": null,
  "last_modified": "2024-10-18T15:22:04.025944Z",
  "mimetype": null,
  "name": "templates",
  "path": "how_to/templates",
  "size": null,
  "type": "directory",
  "writable": true
}